Licensing_MR/__init__.py
Licensing_MR/auth.py
Licensing_MR-0.0.5.dist-info/LICENSE
Licensing_MR-0.0.5.dist-info/METADATA
Licensing_MR-0.0.5.dist-info/WHEEL
Licensing_MR-0.0.5.dist-info/top_level.txt
Licensing_MR-0.0.5.dist-info/RECORD
