Metadata-Version: 2.1
Name: Licensing-MR
Version: 0.0.5
Summary: Licensing Software Package by Manuel Raffl
Author-email: Manuel Raffl <manuraffl003@gmail.com>
Project-URL: Homepage, https://github.com/pypa/sampleproject
Project-URL: Bug Tracker, https://github.com/pypa/sampleproject/issues
Classifier: Programming Language :: Python :: 3
Classifier: License :: OSI Approved :: MIT License
Classifier: Operating System :: OS Independent
Requires-Python: >=3.7
License-File: LICENSE
